bricks/__init__.py
bricks/commons.py
bricks/completion.py
bricks/exceptions.py
bricks/help_printer.py
bricks/helpers.py
bricks/logger.py
bricks/main.py
bricks/schema.py
bricks/executors/__init__.py
bricks/executors/base.py
bricks/executors/bricks.py
bricks/executors/docker.py
bricks/executors/local.py
bricks/executors/native.py
bricks/plugin_kit/__init__.py
bricks/plugin_kit/base.py
bricks/plugin_kit/checks/__init__.py
bricks/plugin_kit/checks/exceptions.py
bricks/plugin_kit/init_steps/__init__.py
bricks/plugin_kit/init_steps/base.py
bricks/plugin_kit/init_steps/checks.py
bricks/plugin_kit/init_steps/file_ops.py
bricks/plugin_kit/init_steps/python_ops.py
bricks/plugins/__init__.py
bricks/plugins/ansible.py
bricks/plugins/bumpversion.py
bricks/plugins/dockercompose.py
bricks/plugins/python_library.py
bricks/plugins/sphinx.py
bricks/plugins/resources/__init__.py
bricks/plugins/resources/python_library.py
tests/__init__.py
tests/test_default.py
woning_bricks-0.3.0.dist-info/METADATA
woning_bricks-0.3.0.dist-info/RECORD
woning_bricks-0.3.0.dist-info/WHEEL
woning_bricks-0.3.0.dist-info/entry_points.txt
woning_bricks-0.3.0.dist-info/top_level.txt
