Metadata-Version: 2.1
Name: woning-bricks
Version: 0.3.0
Summary: Development workflow made easy
Home-page: https://gitlab.com/woning-group/libs/bricks
License: UNKNOWN
Platform: UNKNOWN
Provides-Extra: dev
Requires-Dist: click (>=6)
Requires-Dist: woning-wattle (>=0.4)
Requires-Dist: colorlog
Provides-Extra: dev
Requires-Dist: pytest; extra == 'dev'
Requires-Dist: pycodestyle; extra == 'dev'
Requires-Dist: woning-bricks; extra == 'dev'
Requires-Dist: twine; extra == 'dev'
Requires-Dist: bumpversion; extra == 'dev'
